femm/__init__.py
femm/femm.py
pyfemm-0.1.3.dist-info/LICENSE.txt
pyfemm-0.1.3.dist-info/METADATA
pyfemm-0.1.3.dist-info/WHEEL
pyfemm-0.1.3.dist-info/top_level.txt
pyfemm-0.1.3.dist-info/RECORD
