Metadata-Version: 1.1
Name: pyfemm
Version: 0.1.3
Summary: Python interface to Finite Element Method Magnetics (FEMM)
Home-page: http://www.femm.info/wiki/pyFEMM
Author: David Meeker
Author-email: dmeeker@ieee.org
License: UNKNOWN
Platform: UNKNOWN
Classifier: Development Status :: 3 - Alpha
Classifier: Intended Audience :: Science/Research
Classifier: Operating System :: Microsoft :: Windows
Classifier: Topic :: Scientific/Engineering :: Electronic Design Automation (EDA)
Classifier: License :: Aladdin Free Public License (AFPL)
